percent/__init__.py
ez_percent-0.0.1.dist-info/METADATA
ez_percent-0.0.1.dist-info/WHEEL
ez_percent-0.0.1.dist-info/licenses/LICENSE
ez_percent-0.0.1.dist-info/RECORD
