Metadata-Version: 2.4
Name: ez-percent
Version: 0.0.1
Summary: A comprehensive codebase to calculate percentages.
Project-URL: Homepage, https://github.com/awesome-open-source-projects/percent
Project-URL: Issues, https://github.com/awesome-open-source-projects/percent/issues
Author-email: yolowex <yolowex@gmail.com>
License-Expression: MPL-2.0
License-File: LICENSE
Classifier: Operating System :: OS Independent
Classifier: Programming Language :: Python :: 3
Requires-Python: >=3.9
